w8ing/__init__.py
w8ing/__version__.py
w8ing/utils.py
w8ing/wait.py
w8ing-1.0.2.dist-info/LICENSE
w8ing-1.0.2.dist-info/METADATA
w8ing-1.0.2.dist-info/WHEEL
w8ing-1.0.2.dist-info/top_level.txt
w8ing-1.0.2.dist-info/RECORD
