Metadata-Version: 2.1
Name: w8ing
Version: 1.0.2
Summary: Waiting, for humans.
Home-page: http://pypi.python.org/pypi/w8ing
Author: Imran Mumtaz
Author-email: iomumtaz@gmail.com
License: MIT License
Project-URL: Homepage, https://github.com/ImXron/w8ing
Project-URL: Source, https://github.com/ImXron/w8ing
Project-URL: Tracker, https://github.com/ImXron/w8ing/issues
Keywords: waiting,polling,synchronization,wait until,test tools
Platform: UNKNOWN
Classifier: Development Status :: 4 - Beta
Classifier: License :: OSI Approved :: MIT License
Classifier: Natural Language :: English
Classifier: Operating System :: OS Independent
Classifier: Programming Language :: Python
Classifier: Programming Language :: Python :: 3
Classifier: Programming Language :: Python :: 3.6
Classifier: Programming Language :: Python :: 3.7
Classifier: Programming Language :: Python :: 3.8
Classifier: Topic :: Utilities
